autodistill_vlpart/__init__.py
autodistill_vlpart/predictor.py
autodistill_vlpart/visualizer.py
autodistill_vlpart/vlpart_model.py
autodistill_vlpart-0.1.1.dist-info/LICENSE
autodistill_vlpart-0.1.1.dist-info/METADATA
autodistill_vlpart-0.1.1.dist-info/WHEEL
autodistill_vlpart-0.1.1.dist-info/top_level.txt
autodistill_vlpart-0.1.1.dist-info/RECORD
