Metadata-Version: 2.1
Name: autodistill-vlpart
Version: 0.1.1
Summary: VLPart for use with Autodistill
Home-page: https://github.com/autodistill/autodistill-vlpart
Author: Roboflow
Author-email: support@roboflow.vom
Classifier: Programming Language :: Python :: 3
Classifier: License :: OSI Approved :: MIT License
Classifier: Operating System :: OS Independent
Requires-Python: >=3.7
License-File: LICENSE
Requires-Dist: autodistill
Requires-Dist: supervision
Requires-Dist: torch
Requires-Dist: numpy
Provides-Extra: dev
Requires-Dist: flake8 ; extra == 'dev'
Requires-Dist: black ==22.3.0 ; extra == 'dev'
Requires-Dist: isort ; extra == 'dev'
Requires-Dist: twine ; extra == 'dev'
Requires-Dist: pytest ; extra == 'dev'
Requires-Dist: wheel ; extra == 'dev'
